elasticsearch_fixtures/__init__.py
elasticsearch_fixtures/es_mixer.py
elasticsearch_fixtures-0.1.1.dist-info/LICENSE
elasticsearch_fixtures-0.1.1.dist-info/METADATA
elasticsearch_fixtures-0.1.1.dist-info/WHEEL
elasticsearch_fixtures-0.1.1.dist-info/top_level.txt
elasticsearch_fixtures-0.1.1.dist-info/RECORD
