Metadata-Version: 2.1
Name: elasticsearch-fixtures
Version: 0.1.1
Summary: Mixer-like tool to create test-fixtures for an Elasticsearch index
Home-page: https://github.com/theartling/elasticsearch-fixtures/
Author: Martin Brochhaus
Author-email: mbrochh@gmail.com
License: MIT License
Platform: UNKNOWN
Classifier: Environment :: Web Environment
Classifier: Framework :: Django
Classifier: Framework :: Django :: 2.2
Classifier: Intended Audience :: Developers
Classifier: License :: OSI Approved :: MIT License
Classifier: Operating System :: OS Independent
Classifier: Programming Language :: Python
Classifier: Programming Language :: Python :: 3.6
Classifier: Topic :: Internet :: WWW/HTTP
Classifier: Topic :: Internet :: WWW/HTTP :: Dynamic Content
Requires-Dist: requests (==2.22.0)
